LICENSE
README.md
setup.py
image_mint/__init__.py
image_mint/console.py
image_mint/test.py
image_mint.egg-info/PKG-INFO
image_mint.egg-info/SOURCES.txt
image_mint.egg-info/dependency_links.txt
image_mint.egg-info/entry_points.txt
image_mint.egg-info/requires.txt
image_mint.egg-info/top_level.txt
image_mint/engines/__init__.py
image_mint/engines/bing.py
image_mint/engines/dogpile.py
image_mint/engines/duckduckgo.py
image_mint/engines/google.py
image_mint/engines/yahoo.py