Metadata-Version: 2.1
Name: image-mint
Version: 1.0.0
Summary: image_mint is a python package for searching for and downloading images
Home-page: https://github.com/kouroshparsa/image_mint
Author: Kourosh Parsa
Author-email: kouroshtheking@gmail.com
License: UNKNOWN
Keywords: google,bing,yahoo,images,scraping,search
Platform: UNKNOWN
Classifier: Environment :: Console
Classifier: Programming Language :: Python :: 3
Classifier: License :: OSI Approved :: MIT License
Classifier: Operating System :: OS Independent
License-File: LICENSE
